setup.py
Flask_DbShell.egg-info/PKG-INFO
Flask_DbShell.egg-info/SOURCES.txt
Flask_DbShell.egg-info/dependency_links.txt
Flask_DbShell.egg-info/not-zip-safe
Flask_DbShell.egg-info/requires.txt
Flask_DbShell.egg-info/top_level.txt
flask_dbshell/__init__.py
flask_dbshell/backends/__init__.py
flask_dbshell/backends/mysql.py
flask_dbshell/backends/postgresql.py
flask_dbshell/backends/redis.py
flask_dbshell/backends/sqlite.py