Metadata-Version: 1.1
Name: Flask-DbShell
Version: 1.0
Summary: Django-like dbshell
Home-page: http://github.com/ffeast/flask-dbshell/
Author: ffeast
Author-email: ffeast@gmail.com
License: BSD
Platform: any
Classifier: Environment :: Web Environment
Classifier: Intended Audience :: Developers
Classifier: License :: OSI Approved :: BSD License
Classifier: Operating System :: OS Independent
Classifier: Programming Language :: Python
Classifier: Topic :: Internet :: WWW/HTTP :: Dynamic Content
Classifier: Topic :: Software Development :: Libraries :: Python Modules
